typed_getenv/__init__.py
typed_getenv/_exceptions.py
typed_getenv/_getenv.py
typed_getenv-0.1.2.dist-info/WHEEL
typed_getenv-0.1.2.dist-info/METADATA
typed_getenv-0.1.2.dist-info/RECORD
