Metadata-Version: 2.1
Name: typed-getenv
Version: 0.1.2
Summary: A simple module for environment variable based configuration
Home-page: https://github.com/arseniiarsenii/typed-getenv/
License: Apache 2.0
Author: arseniiarsenii
Author-email: arseniivelichko2@gmail.com
Requires-Python: >=3.7,<4.0
Classifier: License :: Other/Proprietary License
Classifier: Programming Language :: Python :: 3
Classifier: Programming Language :: Python :: 3.10
Classifier: Programming Language :: Python :: 3.7
Classifier: Programming Language :: Python :: 3.8
Classifier: Programming Language :: Python :: 3.9
